metamorph.py
metamorph_cli-1.0.0.dist-info/licenses/LICENSE
metamorph_cli-1.0.0.dist-info/METADATA
metamorph_cli-1.0.0.dist-info/WHEEL
metamorph_cli-1.0.0.dist-info/entry_points.txt
metamorph_cli-1.0.0.dist-info/top_level.txt
metamorph_cli-1.0.0.dist-info/RECORD
