Metadata-Version: 2.4
Name: metamorph-cli
Version: 1.0.0
Summary: Transform your file metadata with ease
Home-page: https://github.com/atridahmetaj/metamorph
Author: Atrid Ahmetaj
Author-email: 
License: MIT
Project-URL: Homepage, https://github.com/atridahmetaj/metamorph
Project-URL: Repository, https://github.com/atridahmetaj/metamorph
Keywords: metadata,pdf,exif,audio,tags,cli
Classifier: Development Status :: 4 - Beta
Classifier: Intended Audience :: Developers
Classifier: Intended Audience :: End Users/Desktop
Classifier: Topic :: Utilities
Classifier: License :: OSI Approved :: MIT License
Classifier: Programming Language :: Python :: 3
Classifier: Programming Language :: Python :: 3.7
Classifier: Programming Language :: Python :: 3.8
Classifier: Programming Language :: Python :: 3.9
Classifier: Programming Language :: Python :: 3.10
Classifier: Programming Language :: Python :: 3.11
Classifier: Programming Language :: Python :: 3.12
Classifier: Programming Language :: Python :: 3.13
Classifier: Operating System :: OS Independent
Classifier: Environment :: Console
Requires-Python: >=3.7
License-File: LICENSE
Requires-Dist: PyPDF2>=3.0.0
Requires-Dist: Pillow>=10.0.0
Requires-Dist: mutagen>=1.47.0
Dynamic: home-page
Dynamic: license-file
Dynamic: requires-python
